funbible/finders/local.py
funbible/finders/online.py
funbible/main.py
funbible-0.0.1.dist-info/METADATA
funbible-0.0.1.dist-info/WHEEL
funbible-0.0.1.dist-info/entry_points.txt
funbible-0.0.1.dist-info/RECORD
